{"textures":[{"image":"theme-resources.png","format":"RGBA8888","size":{"w":196,"h":133},"scale":0.5,"frames":[{"filename":"theme-screen/card-01","rotated":false,"trimmed":false,"sourceSize":{"w":62,"h":129},"spriteSourceSize":{"x":0,"y":0,"w":62,"h":129},"frame":{"x":2,"y":2,"w":62,"h":129}},{"filename":"theme-screen/card-02","rotated":false,"trimmed":false,"sourceSize":{"w":62,"h":129},"spriteSourceSize":{"x":0,"y":0,"w":62,"h":129},"frame":{"x":67,"y":2,"w":62,"h":129}},{"filename":"theme-screen/card-03","rotated":false,"trimmed":false,"sourceSize":{"w":62,"h":129},"spriteSourceSize":{"x":0,"y":0,"w":62,"h":129},"frame":{"x":132,"y":2,"w":62,"h":129}}]}],"meta":{"app":"https://www.codeandweb.com/texturepacker","version":"3.0","smartupdate":"$TexturePacker:SmartUpdate:037507baebfee69b7e7bb49948295bf4:6aca3b15153f3d58aade4786ac8de632:ee82507ec956c55311fa32463b284603$"}}